<manifest alg="2" build="2018.1.0.386" opt="false" iceEnabled="true" iceMarkupVersion="2" iceEnabledOptions="link,responsive,cachebuster,textStyling" exportTarget="other" domain="jose78930.github.io" resolutions="1x" timestamp="1527466936942">
  <folder name="css">
    <file name="site_global.css" crc="45273418"/>
    <file name="master_a-master.css" crc="278816660" ref="index:aplicaciones:acerca-de"/>
    <file name="nomq_preview_master_a-master.css" crc="146622436" ref="index:aplicaciones:acerca-de"/>
    <file name="index.css" crc="3866976304" ref="index"/>
    <file name="nomq_index.css" crc="166461732" ref="index"/>
    <file name="aplicaciones.css" crc="233468832" ref="aplicaciones"/>
    <file name="nomq_aplicaciones.css" crc="3802768651" ref="aplicaciones"/>
    <file name="acerca-de.css" crc="3866976304" ref="acerca-de"/>
    <file name="nomq_acerca-de.css" crc="166461732" ref="acerca-de"/>
  </folder>
  <folder name="scripts">
    <file name="jquery-1.8.3.min.js" crc="209076791" ref="aplicaciones:index:acerca-de"/>
    <file name="museutils.js" crc="340535759" ref="aplicaciones:index:acerca-de"/>
    <file name="whatinput.js" crc="86476730" ref="aplicaciones:index:acerca-de"/>
    <file name="museconfig.js" crc="4286661555" ref="aplicaciones:index:acerca-de"/>
    <file name="jquery.musemenu.js" crc="510910590" ref="aplicaciones:index:acerca-de"/>
    <file name="jquery.watch.js" crc="51536988" ref="aplicaciones:index:acerca-de"/>
    <file name="webpro.js" crc="4059564322" ref="aplicaciones:index:acerca-de"/>
    <file name="musewpslideshow.js" crc="3862962738" ref="aplicaciones"/>
    <file name="jquery.museoverlay.js" crc="4147669564" ref="aplicaciones"/>
    <file name="touchswipe.js" crc="4075097462" ref="aplicaciones"/>
    <file name="musewpdisclosure.js" crc="3883500470" ref="aplicaciones:index:acerca-de"/>
    <file name="html5shiv.js" crc="4241844378" ref="aplicaciones:index:acerca-de"/>
    <file name="jquery.museresponsive.js" crc="527716135" ref="aplicaciones:index:acerca-de"/>
    <file name="require.js" crc="7928878" ref="aplicaciones:index:acerca-de"/>
  </folder>
  <folder name="images">
    <file name="favicon.ico" crc="292395254" ref="aplicaciones"/>
    <file name="solologo2.svg" crc="79868826" seo="true" ref="aplicaciones:index:acerca-de">
      <caption webpage="index" alt=""/>
      <caption webpage="index" alt=""/>
      <caption webpage="index" alt=""/>
      <caption webpage="aplicaciones" alt=""/>
      <caption webpage="aplicaciones" alt=""/>
      <caption webpage="aplicaciones" alt=""/>
      <caption webpage="aplicaciones" alt=""/>
      <caption webpage="acerca-de" alt=""/>
      <caption webpage="acerca-de" alt=""/>
      <caption webpage="acerca-de" alt=""/>
    </file>
    <file name="solologo2_poster_.png" crc="75904228" ref="aplicaciones"/>
    <file name="circleponglogobannertransparente.png" crc="132577648" seo="true" ref="aplicaciones">
      <caption webpage="aplicaciones" alt=""/>
      <caption webpage="aplicaciones" alt=""/>
      <caption webpage="aplicaciones" alt=""/>
      <caption webpage="aplicaciones" alt=""/>
    </file>
    <file name="screen_720x1280_2018-05-27_15-16-35-crop-u6862.png" crc="376710180" seo="true" ref="aplicaciones">
      <caption webpage="aplicaciones" alt=""/>
    </file>
    <file name="screen_720x1280_2018-05-27_15-15-36-crop-u7012.png" crc="111157045" seo="true" ref="aplicaciones">
      <caption webpage="aplicaciones" alt=""/>
    </file>
    <file name="screen_720x1280_2018-05-27_15-15-38-crop-u7039.png" crc="4122624853" seo="true" ref="aplicaciones">
      <caption webpage="aplicaciones" alt=""/>
    </file>
    <file name="screen_720x1280_2018-05-27_15-28-40-crop-u7066.png" crc="3967090023" seo="true" ref="aplicaciones">
      <caption webpage="aplicaciones" alt=""/>
    </file>
    <file name="screen_720x1280_2018-05-27_15-16-08-crop-u7093.png" crc="4115026632" seo="true" ref="aplicaciones">
      <caption webpage="aplicaciones" alt=""/>
    </file>
    <file name="screen_720x1280_2018-05-27_15-28-41-crop-u7120.png" crc="3968261393" seo="true" ref="aplicaciones">
      <caption webpage="aplicaciones" alt=""/>
    </file>
    <file name="screen_720x1280_2018-05-27_15-16-09-crop-u7172.png" crc="495828953" seo="true" ref="aplicaciones">
      <caption webpage="aplicaciones" alt=""/>
    </file>
    <file name="blank.gif" crc="4208392903" ref="aplicaciones:index:acerca-de"/>
    <file name="loading.gif" crc="3815509949" ref="aplicaciones"/>
    <file name="yt_logo_mono_dark.png" crc="34002800" seo="true" ref="aplicaciones:index:acerca-de">
      <caption webpage="index" alt=""/>
      <caption webpage="index" alt=""/>
      <caption webpage="index" alt=""/>
      <caption webpage="aplicaciones" alt=""/>
      <caption webpage="aplicaciones" alt=""/>
      <caption webpage="aplicaciones" alt=""/>
      <caption webpage="aplicaciones" alt=""/>
      <caption webpage="acerca-de" alt=""/>
      <caption webpage="acerca-de" alt=""/>
      <caption webpage="acerca-de" alt=""/>
    </file>
    <file name="abrir.svg" crc="3881540917" ref="aplicaciones:index"/>
    <file name="abrir_poster_u2977.png" crc="229763918" ref="aplicaciones:index"/>
    <file name="cerrar.svg" crc="94584885" ref="aplicaciones:index"/>
    <file name="cerrar_poster_u2930.png" crc="66643228" ref="aplicaciones:index"/>
    <file name="screen_720x1280_2018-05-27_15-16-35-crop-u68622.png" crc="3817839960" seo="true" ref="aplicaciones">
      <caption webpage="aplicaciones" alt=""/>
    </file>
    <file name="screen_720x1280_2018-05-27_15-15-36-crop-u70122.png" crc="433436950" seo="true" ref="aplicaciones">
      <caption webpage="aplicaciones" alt=""/>
    </file>
    <file name="screen_720x1280_2018-05-27_15-15-38-crop-u70392.png" crc="4247914873" seo="true" ref="aplicaciones">
      <caption webpage="aplicaciones" alt=""/>
    </file>
    <file name="screen_720x1280_2018-05-27_15-28-40-crop-u70662.png" crc="276362630" seo="true" ref="aplicaciones">
      <caption webpage="aplicaciones" alt=""/>
    </file>
    <file name="screen_720x1280_2018-05-27_15-16-08-crop-u70932.png" crc="3802630847" seo="true" ref="aplicaciones">
      <caption webpage="aplicaciones" alt=""/>
    </file>
    <file name="screen_720x1280_2018-05-27_15-28-41-crop-u71202.png" crc="4089056455" seo="true" ref="aplicaciones">
      <caption webpage="aplicaciones" alt=""/>
    </file>
    <file name="screen_720x1280_2018-05-27_15-16-09-crop-u71722.png" crc="364145001" seo="true" ref="aplicaciones">
      <caption webpage="aplicaciones" alt=""/>
    </file>
    <file name="screen_720x1280_2018-05-27_15-16-35.png" crc="238236678" seo="true" ref="aplicaciones">
      <caption webpage="aplicaciones" alt=""/>
      <caption webpage="aplicaciones" alt=""/>
      <caption webpage="aplicaciones" alt=""/>
      <caption webpage="aplicaciones" alt=""/>
    </file>
    <file name="screen_720x1280_2018-05-27_15-15-36.png" crc="3925808151" seo="true" ref="aplicaciones">
      <caption webpage="aplicaciones" alt=""/>
      <caption webpage="aplicaciones" alt=""/>
      <caption webpage="aplicaciones" alt=""/>
      <caption webpage="aplicaciones" alt=""/>
    </file>
    <file name="screen_720x1280_2018-05-27_15-15-38.png" crc="4288184230" seo="true" ref="aplicaciones">
      <caption webpage="aplicaciones" alt=""/>
      <caption webpage="aplicaciones" alt=""/>
      <caption webpage="aplicaciones" alt=""/>
      <caption webpage="aplicaciones" alt=""/>
    </file>
    <file name="screen_720x1280_2018-05-27_15-28-40.png" crc="4226570642" seo="true" ref="aplicaciones">
      <caption webpage="aplicaciones" alt=""/>
      <caption webpage="aplicaciones" alt=""/>
      <caption webpage="aplicaciones" alt=""/>
      <caption webpage="aplicaciones" alt=""/>
    </file>
    <file name="screen_720x1280_2018-05-27_15-16-08.png" crc="42597272" seo="true" ref="aplicaciones">
      <caption webpage="aplicaciones" alt=""/>
      <caption webpage="aplicaciones" alt=""/>
      <caption webpage="aplicaciones" alt=""/>
      <caption webpage="aplicaciones" alt=""/>
    </file>
    <file name="screen_720x1280_2018-05-27_15-28-41.png" crc="301061748" seo="true" ref="aplicaciones">
      <caption webpage="aplicaciones" alt=""/>
      <caption webpage="aplicaciones" alt=""/>
      <caption webpage="aplicaciones" alt=""/>
      <caption webpage="aplicaciones" alt=""/>
    </file>
    <file name="screen_720x1280_2018-05-27_15-16-09.png" crc="4077750992" seo="true" ref="aplicaciones">
      <caption webpage="aplicaciones" alt=""/>
      <caption webpage="aplicaciones" alt=""/>
      <caption webpage="aplicaciones" alt=""/>
      <caption webpage="aplicaciones" alt=""/>
    </file>
    <file name="screen_720x1280_2018-05-27_15-16-35-crop-u10721.png" crc="3817839960" seo="true" ref="aplicaciones">
      <caption webpage="aplicaciones" alt=""/>
    </file>
    <file name="screen_720x1280_2018-05-27_15-15-36-crop-u10723.png" crc="433436950" seo="true" ref="aplicaciones">
      <caption webpage="aplicaciones" alt=""/>
    </file>
    <file name="screen_720x1280_2018-05-27_15-15-38-crop-u10725.png" crc="4247914873" seo="true" ref="aplicaciones">
      <caption webpage="aplicaciones" alt=""/>
    </file>
    <file name="screen_720x1280_2018-05-27_15-28-40-crop-u10719.png" crc="276362630" seo="true" ref="aplicaciones">
      <caption webpage="aplicaciones" alt=""/>
    </file>
    <file name="screen_720x1280_2018-05-27_15-16-08-crop-u10713.png" crc="3802630847" seo="true" ref="aplicaciones">
      <caption webpage="aplicaciones" alt=""/>
    </file>
    <file name="screen_720x1280_2018-05-27_15-28-41-crop-u10715.png" crc="4089056455" seo="true" ref="aplicaciones">
      <caption webpage="aplicaciones" alt=""/>
    </file>
    <file name="screen_720x1280_2018-05-27_15-16-09-crop-u10717.png" crc="364145001" seo="true" ref="aplicaciones">
      <caption webpage="aplicaciones" alt=""/>
    </file>
    <file name="screen_720x1280_2018-05-27_15-16-35-crop-u107212.png" crc="3817839960" seo="true" ref="aplicaciones">
      <caption webpage="aplicaciones" alt=""/>
    </file>
    <file name="screen_720x1280_2018-05-27_15-15-36-crop-u107232.png" crc="433436950" seo="true" ref="aplicaciones">
      <caption webpage="aplicaciones" alt=""/>
    </file>
    <file name="screen_720x1280_2018-05-27_15-15-38-crop-u107252.png" crc="4247914873" seo="true" ref="aplicaciones">
      <caption webpage="aplicaciones" alt=""/>
    </file>
    <file name="screen_720x1280_2018-05-27_15-28-40-crop-u107192.png" crc="276362630" seo="true" ref="aplicaciones">
      <caption webpage="aplicaciones" alt=""/>
    </file>
    <file name="screen_720x1280_2018-05-27_15-16-08-crop-u107132.png" crc="3802630847" seo="true" ref="aplicaciones">
      <caption webpage="aplicaciones" alt=""/>
    </file>
    <file name="screen_720x1280_2018-05-27_15-28-41-crop-u107152.png" crc="4089056455" seo="true" ref="aplicaciones">
      <caption webpage="aplicaciones" alt=""/>
    </file>
    <file name="screen_720x1280_2018-05-27_15-16-09-crop-u107172.png" crc="364145001" seo="true" ref="aplicaciones">
      <caption webpage="aplicaciones" alt=""/>
    </file>
  </folder>
  <file name="aplicaciones.html" crc="483982490" seo="true" mt="1527466899501" redirect="true"/>
  <file name="index.html" crc="89376861" seo="true" mt="1527466848959" redirect="true"/>
  <file name="acerca-de.html" crc="4098611003" seo="true" mt="1527466848959" redirect="true"/>
</manifest>